{
  "sections": {
    "8d8fc6c0-b9b4-42df-970b-dde33ccf020f": {
      "type": "slideshow",
      "blocks": {
        "template--14724125818958__8d8fc6c0-b9b4-42df-970b-dde33ccf020f-16753453586fd3491a-0": {
          "type": "hero",
          "settings": {
            "top_subheading": "FEATURED SALE",
            "title": "<p>Finnish Valentine's Gifts<\/p>",
            "title_size": 70,
            "subheading": "Save on Jewelry, Candy, Beauty & More!",
            "link": "",
            "link_text": "",
            "link_2": "",
            "link_text_2": "",
            "color_accent": "#ffffff",
            "text_align": "vertical-center horizontal-center",
            "image": "shopify:\/\/shop_images\/Untitled_design_11.jpg",
            "image_mobile": "shopify:\/\/shop_images\/Untitled_design_-_2023-02-02T104643.768.png",
            "overlay_opacity": 16,
            "focal_point": "center center"
          }
        }
      },
      "block_order": [
        "template--14724125818958__8d8fc6c0-b9b4-42df-970b-dde33ccf020f-16753453586fd3491a-0"
      ],
      "settings": {
        "full_width": true,
        "desktop_size": 0,
        "mobile_size": 10,
        "style": "arrows",
        "autoplay": true,
        "autoplay_speed": 7
      }
    },
    "promo-grid": {
      "type": "promo-grid",
      "disabled": true,
      "blocks": {
        "banner": {
          "type": "banner",
          "disabled": true,
          "settings": {
            "heading": "The Legend of St. Urho",
            "text": "March 16th is St. Urho's Day!",
            "link": "",
            "label": "Read Now",
            "color_scheme": "5"
          }
        },
        "advanced": {
          "type": "advanced",
          "settings": {
            "subheading": "FEATURED SALE",
            "heading": "Finnish Valentine's Gifts",
            "textarea": "Save on Jewelry, Candy, Beauty & More!",
            "cta_text1": "",
            "cta_link1": "",
            "cta_text2": "",
            "cta_link2": "",
            "image": "shopify:\/\/shop_images\/Untitled_design_1.jpg",
            "video_url": "",
            "width": "100",
            "height": 160,
            "text_align": "vertical-center horizontal-center",
            "focal_point": "center",
            "color_accent": "#ffffff"
          }
        }
      },
      "block_order": [
        "banner",
        "advanced"
      ],
      "settings": {
        "full_width": true,
        "gutter_size": 0,
        "space_above": false,
        "space_below": false
      }
    },
    "featured-collection": {
      "type": "featured-collection",
      "settings": {
        "title": "",
        "home_featured_products": "vday-offers",
        "count": 5,
        "mobile_scrollable": true,
        "view_all": false,
        "divider": false
      }
    },
    "3a8c3712-87f9-46ae-afb7-ae6dfcba7bab": {
      "type": "slideshow",
      "blocks": {
        "template--14724125818958__3a8c3712-87f9-46ae-afb7-ae6dfcba7bab-16753009564d7bbe2b-0": {
          "type": "hero",
          "settings": {
            "top_subheading": "",
            "title": "<p>Finnish Jewlery Sale<\/p>",
            "title_size": 70,
            "subheading": "ALL FINNISH JEWELRY ON SALE!",
            "link": "shopify:\/\/collections\/finnish-jewelry",
            "link_text": "Shop Jewelry Sale",
            "link_2": "",
            "link_text_2": "",
            "color_accent": "#941d1d",
            "text_align": "vertical-center horizontal-center",
            "image": "shopify:\/\/shop_images\/Untitled_design_4.jpg",
            "image_mobile": "shopify:\/\/shop_images\/Untitled_design_5_b248298c-fa15-44d3-980e-df5cc053555e.jpg",
            "overlay_opacity": 0,
            "focal_point": "center center"
          }
        }
      },
      "block_order": [
        "template--14724125818958__3a8c3712-87f9-46ae-afb7-ae6dfcba7bab-16753009564d7bbe2b-0"
      ],
      "settings": {
        "full_width": true,
        "desktop_size": 0,
        "mobile_size": 0,
        "style": "arrows",
        "autoplay": true,
        "autoplay_speed": 7
      }
    },
    "featured-collections": {
      "type": "featured-collections",
      "blocks": {
        "collection1": {
          "type": "collection",
          "settings": {
            "collection": "finnfeelings-jewelry",
            "title": ""
          }
        },
        "collection2": {
          "type": "collection",
          "settings": {
            "collection": "kalevala-jewelry",
            "title": ""
          }
        },
        "collection6": {
          "type": "collection",
          "settings": {
            "collection": "lumoava-jewelry",
            "title": ""
          }
        },
        "collection4": {
          "type": "collection",
          "settings": {
            "collection": "valona-jewelry",
            "title": ""
          }
        },
        "collection3": {
          "type": "collection",
          "settings": {
            "collection": "pohjolan-helmi-jewelry",
            "title": ""
          }
        },
        "collection5": {
          "type": "collection",
          "settings": {
            "collection": "chao-eero-finnish-jewelry",
            "title": ""
          }
        }
      },
      "block_order": [
        "collection1",
        "collection2",
        "collection6",
        "collection4",
        "collection3",
        "collection5"
      ],
      "settings": {
        "title": "",
        "divider": false
      }
    },
    "featured-collection3": {
      "type": "featured-collection",
      "settings": {
        "title": "",
        "home_featured_products": "finnish-jewelry",
        "count": 5,
        "mobile_scrollable": true,
        "view_all": false,
        "divider": false
      }
    },
    "1559babe-6f49-4f50-9277-8b873b8d47dd": {
      "type": "slideshow",
      "blocks": {
        "template--14724125818958__1559babe-6f49-4f50-9277-8b873b8d47dd-16753009564d7bbe2b-0": {
          "type": "hero",
          "settings": {
            "top_subheading": "",
            "title": "<p>Finnish Candy Sale<\/p>",
            "title_size": 70,
            "subheading": "ALL FINNISH CANDY ON SALE!",
            "link": "shopify:\/\/collections\/finnish-candy-and-food",
            "link_text": "Shop Candy Sale",
            "link_2": "",
            "link_text_2": "",
            "color_accent": "#941d1d",
            "text_align": "vertical-center horizontal-center",
            "image": "shopify:\/\/shop_images\/Untitled_design_8_3d08cec5-ed3c-4035-a8c4-7a620ee52cd8.jpg",
            "image_mobile": "shopify:\/\/shop_images\/Untitled_design_6_914e5685-9425-42ee-92bf-d10c6254ae7f.jpg",
            "overlay_opacity": 10,
            "focal_point": "center center"
          }
        }
      },
      "block_order": [
        "template--14724125818958__1559babe-6f49-4f50-9277-8b873b8d47dd-16753009564d7bbe2b-0"
      ],
      "settings": {
        "full_width": true,
        "desktop_size": 0,
        "mobile_size": 0,
        "style": "arrows",
        "autoplay": true,
        "autoplay_speed": 7
      }
    },
    "75029e64-53f0-412a-ba1a-8ae4576e6f11": {
      "type": "featured-collections",
      "blocks": {
        "template--14724125818958__75029e64-53f0-412a-ba1a-8ae4576e6f11-1675301368786c0b13-0": {
          "type": "collection",
          "settings": {
            "collection": "finnish-chocolate",
            "title": ""
          }
        },
        "template--14724125818958__75029e64-53f0-412a-ba1a-8ae4576e6f11-1675301368786c0b13-1": {
          "type": "collection",
          "settings": {
            "collection": "finnish-licorice",
            "title": ""
          }
        },
        "template--14724125818958__75029e64-53f0-412a-ba1a-8ae4576e6f11-1675301368786c0b13-2": {
          "type": "collection",
          "settings": {
            "collection": "crispbread-and-cookies",
            "title": ""
          }
        },
        "template--14724125818958__75029e64-53f0-412a-ba1a-8ae4576e6f11-1675301368786c0b13-3": {
          "type": "collection",
          "settings": {
            "collection": "finnish-coffee-tea",
            "title": ""
          }
        },
        "template--14724125818958__75029e64-53f0-412a-ba1a-8ae4576e6f11-1675301368786c0b13-4": {
          "type": "collection",
          "settings": {
            "collection": "finnish-mustard",
            "title": ""
          }
        },
        "template--14724125818958__75029e64-53f0-412a-ba1a-8ae4576e6f11-1675301368786c0b13-5": {
          "type": "collection",
          "settings": {
            "collection": "finnish-candy-and-food",
            "title": "All Candy"
          }
        }
      },
      "block_order": [
        "template--14724125818958__75029e64-53f0-412a-ba1a-8ae4576e6f11-1675301368786c0b13-0",
        "template--14724125818958__75029e64-53f0-412a-ba1a-8ae4576e6f11-1675301368786c0b13-1",
        "template--14724125818958__75029e64-53f0-412a-ba1a-8ae4576e6f11-1675301368786c0b13-2",
        "template--14724125818958__75029e64-53f0-412a-ba1a-8ae4576e6f11-1675301368786c0b13-3",
        "template--14724125818958__75029e64-53f0-412a-ba1a-8ae4576e6f11-1675301368786c0b13-4",
        "template--14724125818958__75029e64-53f0-412a-ba1a-8ae4576e6f11-1675301368786c0b13-5"
      ],
      "settings": {
        "title": "",
        "divider": false
      }
    },
    "featured-collection2": {
      "type": "featured-collection",
      "settings": {
        "title": "",
        "home_featured_products": "finnish-candy-and-food",
        "count": 5,
        "mobile_scrollable": true,
        "view_all": false,
        "divider": false
      }
    },
    "967587b2-4640-4fbc-b261-8d455ba28a66": {
      "type": "slideshow",
      "blocks": {
        "template--14724125818958__967587b2-4640-4fbc-b261-8d455ba28a66-167535103430f22c11-0": {
          "type": "hero",
          "settings": {
            "top_subheading": "",
            "title": "<p>Finnish Beauty Sale<\/p>",
            "title_size": 70,
            "subheading": "ALL BATH & BODY ON SALE!",
            "link": "shopify:\/\/collections\/bath-body",
            "link_text": "Shop Beauty Sale",
            "link_2": "",
            "link_text_2": "",
            "color_accent": "#941d1d",
            "text_align": "vertical-center horizontal-center",
            "image": "shopify:\/\/shop_images\/Untitled_design_9.jpg",
            "image_mobile": "shopify:\/\/shop_images\/Untitled_design_-_2023-02-02T102059.344.png",
            "overlay_opacity": 0,
            "focal_point": "center center"
          }
        }
      },
      "block_order": [
        "template--14724125818958__967587b2-4640-4fbc-b261-8d455ba28a66-167535103430f22c11-0"
      ],
      "settings": {
        "full_width": true,
        "desktop_size": 0,
        "mobile_size": 0,
        "style": "arrows",
        "autoplay": true,
        "autoplay_speed": 7
      }
    },
    "b5829ce5-53b7-44f6-8e4f-b2cbaf3b3d74": {
      "type": "featured-collection",
      "settings": {
        "title": "",
        "home_featured_products": "bath-body",
        "count": 10,
        "mobile_scrollable": true,
        "view_all": true,
        "divider": false
      }
    },
    "promo-grid2": {
      "type": "promo-grid",
      "disabled": true,
      "blocks": {
        "simple": {
          "type": "simple",
          "settings": {
            "link": "",
            "text": "",
            "width": "50",
            "height": 300
          }
        },
        "advanced": {
          "type": "advanced",
          "settings": {
            "subheading": "",
            "heading": "Announce your promotion",
            "textarea": "Include the smaller details of your promotion in text below the title.",
            "cta_text1": "Shop This",
            "cta_link1": "",
            "cta_text2": "Shop All",
            "cta_link2": "",
            "video_url": "",
            "width": "50",
            "height": 500,
            "text_align": "vertical-center horizontal-center",
            "focal_point": "center",
            "color_accent": "#ffffff"
          }
        }
      },
      "block_order": [
        "simple",
        "advanced"
      ],
      "settings": {
        "full_width": false,
        "gutter_size": 20,
        "space_above": false,
        "space_below": false
      }
    },
    "main-collection": {
      "type": "main-collection",
      "disabled": true,
      "blocks": {
        "collection_description": {
          "type": "collection_description",
          "disabled": true,
          "settings": {
          }
        },
        "subcollections": {
          "type": "subcollections",
          "settings": {
          }
        },
        "product_grid": {
          "type": "product_grid",
          "settings": {
            "grid_style": "small"
          }
        }
      },
      "block_order": [
        "collection_description",
        "subcollections",
        "product_grid"
      ],
      "settings": {
        "enable_sidebar": true,
        "collapse_filters": false,
        "enable_color_swatches": false,
        "enable_sort": true
      }
    }
  },
  "order": [
    "8d8fc6c0-b9b4-42df-970b-dde33ccf020f",
    "promo-grid",
    "featured-collection",
    "3a8c3712-87f9-46ae-afb7-ae6dfcba7bab",
    "featured-collections",
    "featured-collection3",
    "1559babe-6f49-4f50-9277-8b873b8d47dd",
    "75029e64-53f0-412a-ba1a-8ae4576e6f11",
    "featured-collection2",
    "967587b2-4640-4fbc-b261-8d455ba28a66",
    "b5829ce5-53b7-44f6-8e4f-b2cbaf3b3d74",
    "promo-grid2",
    "main-collection"
  ]
}
